{
  "schema_version": "1.1.0",
  "date_utc": "2026-04-22",
  "generated_at_utc": "2026-04-22T09:19:33Z",
  "pipeline": {
    "name": "daily_sentiment_data_fetch",
    "anchor_keyword": "Federal Reserve",
    "request_timeout_seconds": 15,
    "request_retries": 3
  },
  "source_health": {
    "polymarket": {
      "status": "ok",
      "row_count": 30,
      "ok_count": 30,
      "empty_count": 0,
      "error_count": 0
    },
    "google_trends": {
      "status": "partial",
      "row_count": 14,
      "ok_count": 0,
      "empty_count": 0,
      "error_count": 18
    },
    "wikipedia_pageviews": {
      "status": "ok",
      "row_count": 10,
      "ok_count": 10,
      "empty_count": 0,
      "error_count": 0
    }
  },
  "sources": {
    "polymarket": {
      "status": "ok",
      "meta": {
        "requested_limit": 30
      },
      "summary": {
        "total_rows": 30,
        "top_questions_by_volume_24h": [
          {
            "question": "Will Bitcoin hit $150k by June 30, 2026?",
            "volume_24h": 5821652.894196,
            "yes_price": 0.0135,
            "market_type": "binary"
          },
          {
            "question": "US x Iran permanent peace deal by April 22, 2026?",
            "volume_24h": 5520100.854613998,
            "yes_price": 0.019,
            "market_type": "binary"
          },
          {
            "question": "Iran x Israel/US conflict ends by April 7?",
            "volume_24h": 4328200.489911007,
            "yes_price": 0.9975,
            "market_type": "binary"
          },
          {
            "question": "Strait of Hormuz traffic returns to normal by end of April?",
            "volume_24h": 2971417.5243400005,
            "yes_price": 0.115,
            "market_type": "binary"
          },
          {
            "question": "Iran x Israel/US conflict ends by May 15?",
            "volume_24h": 2596399.589361,
            "yes_price": 0.9985,
            "market_type": "binary"
          }
        ],
        "binary_markets": 28,
        "non_binary_markets": 2
      },
      "data": [
        {
          "source": "polymarket",
          "id": "573655",
          "question": "Will Bitcoin hit $150k by June 30, 2026?",
          "slug": "will-bitcoin-hit-150k-by-june-30-2026",
          "market_type": "binary",
          "yes_price": 0.0135,
          "no_price": 0.9865,
          "outcomes": [
            "Yes",
            "No"
          ],
          "outcome_prices": [
            0.0135,
            0.9865
          ],
          "volume_24h": 5821652.894196,
          "liquidity": 19822.55555,
          "active": true,
          "closed": false,
          "end_date": "2026-07-01T04:00:00Z",
          "status": "ok"
        },
        {
          "source": "polymarket",
          "id": "1919417",
          "question": "US x Iran permanent peace deal by April 22, 2026?",
          "slug": "us-x-iran-permanent-peace-deal-by-april-22-2026",
          "market_type": "binary",
          "yes_price": 0.019,
          "no_price": 0.981,
          "outcomes": [
            "Yes",
            "No"
          ],
          "outcome_prices": [
            0.019,
            0.981
          ],
          "volume_24h": 5520100.854613998,
          "liquidity": 224556.00488,
          "active": true,
          "closed": false,
          "end_date": "2026-04-22T00:00:00Z",
          "status": "ok"
        },
        {
          "source": "polymarket",
          "id": "1706766",
          "question": "Iran x Israel/US conflict ends by April 7?",
          "slug": "iran-x-israelus-conflict-ends-by-april-7-346",
          "market_type": "binary",
          "yes_price": 0.9975,
          "no_price": 0.0025,
          "outcomes": [
            "Yes",
            "No"
          ],
          "outcome_prices": [
            0.9975,
            0.0025
          ],
          "volume_24h": 4328200.489911007,
          "liquidity": 1758337.02556,
          "active": true,
          "closed": false,
          "end_date": "2026-04-07T00:00:00Z",
          "status": "ok"
        },
        {
          "source": "polymarket",
          "id": "1540766",
          "question": "Strait of Hormuz traffic returns to normal by end of April?",
          "slug": "strait-of-hormuz-traffic-returns-to-normal-by-april-30",
          "market_type": "binary",
          "yes_price": 0.115,
          "no_price": 0.885,
          "outcomes": [
            "Yes",
            "No"
          ],
          "outcome_prices": [
            0.115,
            0.885
          ],
          "volume_24h": 2971417.5243400005,
          "liquidity": 502539.8075,
          "active": true,
          "closed": false,
          "end_date": "2026-04-30T00:00:00Z",
          "status": "ok"
        },
        {
          "source": "polymarket",
          "id": "1484914",
          "question": "Iran x Israel/US conflict ends by May 15?",
          "slug": "iran-x-israelus-conflict-ends-by-may-15-562-372-916-721-496",
          "market_type": "binary",
          "yes_price": 0.9985,
          "no_price": 0.0015,
          "outcomes": [
            "Yes",
            "No"
          ],
          "outcome_prices": [
            0.9985,
            0.0015
          ],
          "volume_24h": 2596399.589361,
          "liquidity": 1522381.71878,
          "active": true,
          "closed": false,
          "end_date": "2026-05-15T00:00:00Z",
          "status": "ok"
        },
        {
          "source": "polymarket",
          "id": "1567746",
          "question": "Iran x Israel/US conflict ends by April 15?",
          "slug": "iran-x-israelus-conflict-ends-by-april-15-618-586-982",
          "market_type": "binary",
          "yes_price": 0.9975,
          "no_price": 0.0025,
          "outcomes": [
            "Yes",
            "No"
          ],
          "outcome_prices": [
            0.9975,
            0.0025
          ],
          "volume_24h": 2326530.241561997,
          "liquidity": 747182.71118,
          "active": true,
          "closed": false,
          "end_date": "2026-04-15T00:00:00Z",
          "status": "ok"
        },
        {
          "source": "polymarket",
          "id": "669662",
          "question": "Will there be no change in Fed interest rates after the April 2026 meeting?",
          "slug": "will-there-be-no-change-in-fed-interest-rates-after-the-april-2026-meeting",
          "market_type": "binary",
          "yes_price": 0.9935,
          "no_price": 0.0065,
          "outcomes": [
            "Yes",
            "No"
          ],
          "outcome_prices": [
            0.9935,
            0.0065
          ],
          "volume_24h": 2209434.762801,
          "liquidity": 2121610.42297,
          "active": true,
          "closed": false,
          "end_date": "2026-04-29T00:00:00Z",
          "status": "ok"
        },
        {
          "source": "polymarket",
          "id": "1919421",
          "question": "US x Iran permanent peace deal by April 30, 2026?",
          "slug": "us-x-iran-permanent-peace-deal-by-april-30-2026-925",
          "market_type": "binary",
          "yes_price": 0.145,
          "no_price": 0.855,
          "outcomes": [
            "Yes",
            "No"
          ],
          "outcome_prices": [
            0.145,
            0.855
          ],
          "volume_24h": 2137958.7420779946,
          "liquidity": 572875.6551,
          "active": true,
          "closed": false,
          "end_date": "2026-04-30T00:00:00Z",
          "status": "ok"
        },
        {
          "source": "polymarket",
          "id": "558943",
          "question": "Will USA win the 2026 FIFA World Cup?",
          "slug": "will-usa-win-the-2026-fifa-world-cup-467",
          "market_type": "binary",
          "yes_price": 0.0125,
          "no_price": 0.9875,
          "outcomes": [
            "Yes",
            "No"
          ],
          "outcome_prices": [
            0.0125,
            0.9875
          ],
          "volume_24h": 2077136.6515020004,
          "liquidity": 2527499.42514,
          "active": true,
          "closed": false,
          "end_date": "2026-07-20T00:00:00Z",
          "status": "ok"
        },
        {
          "source": "polymarket",
          "id": "665374",
          "question": "Will the U.S. invade Iran before 2027?",
          "slug": "will-the-us-invade-iran-before-2027",
          "market_type": "binary",
          "yes_price": 0.305,
          "no_price": 0.695,
          "outcomes": [
            "Yes",
            "No"
          ],
          "outcome_prices": [
            0.305,
            0.695
          ],
          "volume_24h": 2030660.8604640327,
          "liquidity": 300925.0301,
          "active": true,
          "closed": false,
          "end_date": "2026-12-31T00:00:00Z",
          "status": "ok"
        },
        {
          "source": "polymarket",
          "id": "1484915",
          "question": "Iran x Israel/US conflict ends by June 30?",
          "slug": "iran-x-israelus-conflict-ends-by-june-30-813-454-138-725",
          "market_type": "binary",
          "yes_price": 0.9985,
          "no_price": 0.0015,
          "outcomes": [
            "Yes",
            "No"
          ],
          "outcome_prices": [
            0.9985,
            0.0015
          ],
          "volume_24h": 1437826.4901630008,
          "liquidity": 1585253.08652,
          "active": true,
          "closed": false,
          "end_date": "2026-06-30T00:00:00Z",
          "status": "ok"
        },
        {
          "source": "polymarket",
          "id": "1507751",
          "question": "Will the Iranian regime fall by April 30?",
          "slug": "will-the-iranian-regime-fall-by-april-30",
          "market_type": "binary",
          "yes_price": 0.0055,
          "no_price": 0.9945,
          "outcomes": [
            "Yes",
            "No"
          ],
          "outcome_prices": [
            0.0055,
            0.9945
          ],
          "volume_24h": 1278320.0068060004,
          "liquidity": 3438092.3105,
          "active": true,
          "closed": false,
          "end_date": "2026-04-30T00:00:00Z",
          "status": "ok"
        },
        {
          "source": "polymarket",
          "id": "1959319",
          "question": "US x Iran diplomatic meeting by April 22, 2026?",
          "slug": "us-x-iran-diplomatic-meeting-by-april-22-2026-321-831",
          "market_type": "binary",
          "yes_price": 0.0055,
          "no_price": 0.9945,
          "outcomes": [
            "Yes",
            "No"
          ],
          "outcome_prices": [
            0.0055,
            0.9945
          ],
          "volume_24h": 1237573.2409640076,
          "liquidity": 85615.56473,
          "active": true,
          "closed": false,
          "end_date": "2026-04-30T00:00:00Z",
          "status": "ok"
        },
        {
          "source": "polymarket",
          "id": "669661",
          "question": "Will the Fed decrease interest rates by 25 bps after the April 2026 meeting?",
          "slug": "will-the-fed-decrease-interest-rates-by-25-bps-after-the-april-2026-meeting",
          "market_type": "binary",
          "yes_price": 0.0025,
          "no_price": 0.9975,
          "outcomes": [
            "Yes",
            "No"
          ],
          "outcome_prices": [
            0.0025,
            0.9975
          ],
          "volume_24h": 1145117.876309999,
          "liquidity": 759125.31885,
          "active": true,
          "closed": false,
          "end_date": "2026-04-29T00:00:00Z",
          "status": "ok"
        },
        {
          "source": "polymarket",
          "id": "553862",
          "question": "Will the Boston Celtics win the 2026 NBA Finals?",
          "slug": "will-the-boston-celtics-win-the-2026-nba-finals",
          "market_type": "binary",
          "yes_price": 0.121,
          "no_price": 0.879,
          "outcomes": [
            "Yes",
            "No"
          ],
          "outcome_prices": [
            0.121,
            0.879
          ],
          "volume_24h": 1113312.8496100002,
          "liquidity": 143201.4102,
          "active": true,
          "closed": false,
          "end_date": "2026-07-01T00:00:00Z",
          "status": "ok"
        },
        {
          "source": "polymarket",
          "id": "2014162",
          "question": "LoL: KT Rolster vs Kiwoom DRX - Game 1 Winner",
          "slug": "lol-kt-drx-2026-04-22-game1",
          "market_type": "non_binary",
          "yes_price": null,
          "no_price": null,
          "outcomes": [
            "KT Rolster",
            "Kiwoom DRX"
          ],
          "outcome_prices": [
            0.9995,
            0.0005
          ],
          "volume_24h": 1077963.6831820002,
          "liquidity": 230218.79232,
          "active": true,
          "closed": false,
          "end_date": "2026-04-22T12:00:00Z",
          "status": "ok"
        },
        {
          "source": "polymarket",
          "id": "558984",
          "question": "Will Czechia win the 2026 FIFA World Cup?",
          "slug": "will-czechia-win-the-2026-fifa-world-cup",
          "market_type": "binary",
          "yes_price": 0.0025,
          "no_price": 0.9975,
          "outcomes": [
            "Yes",
            "No"
          ],
          "outcome_prices": [
            0.0025,
            0.9975
          ],
          "volume_24h": 1043742.8634799999,
          "liquidity": 4823941.27311,
          "active": true,
          "closed": false,
          "end_date": "2026-07-20T00:00:00Z",
          "status": "ok"
        },
        {
          "source": "polymarket",
          "id": "947289",
          "question": "Will Roberto Sánchez Palomino win the 2026 Peruvian presidential election?",
          "slug": "will-roberto-snchez-palomino-win-the-2026-peruvian-presidential-election",
          "market_type": "binary",
          "yes_price": 0.2345,
          "no_price": 0.7655,
          "outcomes": [
            "Yes",
            "No"
          ],
          "outcome_prices": [
            0.2345,
            0.7655
          ],
          "volume_24h": 1024862.419367,
          "liquidity": 165628.04346,
          "active": true,
          "closed": false,
          "end_date": "2026-06-07T00:00:00Z",
          "status": "ok"
        },
        {
          "source": "polymarket",
          "id": "553866",
          "question": "Will the San Antonio Spurs win the 2026 NBA Finals?",
          "slug": "will-the-san-antonio-spurs-win-the-2026-nba-finals",
          "market_type": "binary",
          "yes_price": 0.121,
          "no_price": 0.879,
          "outcomes": [
            "Yes",
            "No"
          ],
          "outcome_prices": [
            0.121,
            0.879
          ],
          "volume_24h": 1019839.1687049998,
          "liquidity": 393013.39282,
          "active": true,
          "closed": false,
          "end_date": "2026-07-01T00:00:00Z",
          "status": "ok"
        },
        {
          "source": "polymarket",
          "id": "1611267",
          "question": "Kharg Island no longer under Iranian control by April 30?",
          "slug": "kharg-island-no-longer-under-iranian-control-by-april-30-912",
          "market_type": "binary",
          "yes_price": 0.073,
          "no_price": 0.927,
          "outcomes": [
            "Yes",
            "No"
          ],
          "outcome_prices": [
            0.073,
            0.927
          ],
          "volume_24h": 943207.8064029993,
          "liquidity": 136971.13238,
          "active": true,
          "closed": false,
          "end_date": "2026-04-30T23:55:00Z",
          "status": "ok"
        },
        {
          "source": "polymarket",
          "id": "2036399",
          "question": "US x Iran ceasefire extended by April 22, 2026?",
          "slug": "us-x-iran-ceasefire-extended-by-april-22-2026",
          "market_type": "binary",
          "yes_price": 0.135,
          "no_price": 0.865,
          "outcomes": [
            "Yes",
            "No"
          ],
          "outcome_prices": [
            0.135,
            0.865
          ],
          "volume_24h": 930661.1129820021,
          "liquidity": 49213.3316,
          "active": true,
          "closed": false,
          "end_date": "2026-04-21T00:00:00Z",
          "status": "ok"
        },
        {
          "source": "polymarket",
          "id": "669660",
          "question": "Will the Fed decrease interest rates by 50+ bps after the April 2026 meeting?",
          "slug": "will-the-fed-decrease-interest-rates-by-50-bps-after-the-april-2026-meeting",
          "market_type": "binary",
          "yes_price": 0.0015,
          "no_price": 0.9985,
          "outcomes": [
            "Yes",
            "No"
          ],
          "outcome_prices": [
            0.0015,
            0.9985
          ],
          "volume_24h": 912987.1700000009,
          "liquidity": 8849917.23738,
          "active": true,
          "closed": false,
          "end_date": "2026-04-29T00:00:00Z",
          "status": "ok"
        },
        {
          "source": "polymarket",
          "id": "669663",
          "question": "Will the Fed increase interest rates by 25+ bps after the April 2026 meeting?",
          "slug": "will-the-fed-increase-interest-rates-by-25-bps-after-the-april-2026-meeting",
          "market_type": "binary",
          "yes_price": 0.0025,
          "no_price": 0.9975,
          "outcomes": [
            "Yes",
            "No"
          ],
          "outcome_prices": [
            0.0025,
            0.9975
          ],
          "volume_24h": 879177.9238060002,
          "liquidity": 1504691.89447,
          "active": true,
          "closed": false,
          "end_date": "2026-04-29T00:00:00Z",
          "status": "ok"
        },
        {
          "source": "polymarket",
          "id": "1733817",
          "question": "Trump out as President by April 30?",
          "slug": "trump-out-as-president-by-april-30",
          "market_type": "binary",
          "yes_price": 0.0045,
          "no_price": 0.9955,
          "outcomes": [
            "Yes",
            "No"
          ],
          "outcome_prices": [
            0.0045,
            0.9955
          ],
          "volume_24h": 853659.4391800003,
          "liquidity": 2154628.43444,
          "active": true,
          "closed": false,
          "end_date": "2026-04-30T00:00:00Z",
          "status": "ok"
        },
        {
          "source": "polymarket",
          "id": "553869",
          "question": "Will the Philadelphia 76ers win the 2026 NBA Finals?",
          "slug": "will-the-philadelphia-76ers-win-the-2026-nba-finals",
          "market_type": "binary",
          "yes_price": 0.0045,
          "no_price": 0.9955,
          "outcomes": [
            "Yes",
            "No"
          ],
          "outcome_prices": [
            0.0045,
            0.9955
          ],
          "volume_24h": 816510.9503829998,
          "liquidity": 619795.75773,
          "active": true,
          "closed": false,
          "end_date": "2026-07-01T00:00:00Z",
          "status": "ok"
        },
        {
          "source": "polymarket",
          "id": "1500754",
          "question": "Will Kevin Warsh be confirmed as Fed Chair?",
          "slug": "will-kevin-warsh-be-confirmed-as-fed-chair",
          "market_type": "binary",
          "yes_price": 0.943,
          "no_price": 0.057,
          "outcomes": [
            "Yes",
            "No"
          ],
          "outcome_prices": [
            0.943,
            0.057
          ],
          "volume_24h": 778429.3443509992,
          "liquidity": 102878.9774,
          "active": true,
          "closed": false,
          "end_date": "2026-10-31T00:00:00Z",
          "status": "ok"
        },
        {
          "source": "polymarket",
          "id": "2045464",
          "question": "Dota 2: GamerLegion vs Heroic - Game 1 Winner",
          "slug": "dota2-gl-heroic-2026-04-22-game1",
          "market_type": "non_binary",
          "yes_price": null,
          "no_price": null,
          "outcomes": [
            "GamerLegion",
            "Heroic"
          ],
          "outcome_prices": [
            0.0005,
            0.9995
          ],
          "volume_24h": 729553.2982359976,
          "liquidity": 512181.7478,
          "active": true,
          "closed": false,
          "end_date": "2026-04-22T13:00:00Z",
          "status": "ok"
        },
        {
          "source": "polymarket",
          "id": "553879",
          "question": "Will the Portland Trail Blazers win the 2026 NBA Finals?",
          "slug": "will-the-portland-trail-blazers-win-the-2026-nba-finals",
          "market_type": "binary",
          "yes_price": 0.0045,
          "no_price": 0.9955,
          "outcomes": [
            "Yes",
            "No"
          ],
          "outcome_prices": [
            0.0045,
            0.9955
          ],
          "volume_24h": 684106.1444620002,
          "liquidity": 1429424.47701,
          "active": true,
          "closed": false,
          "end_date": "2026-07-01T00:00:00Z",
          "status": "ok"
        },
        {
          "source": "polymarket",
          "id": "1707932",
          "question": "Will the Iranian regime fall by May 31?",
          "slug": "will-the-iranian-regime-fall-by-may-31",
          "market_type": "binary",
          "yes_price": 0.047,
          "no_price": 0.953,
          "outcomes": [
            "Yes",
            "No"
          ],
          "outcome_prices": [
            0.047,
            0.953
          ],
          "volume_24h": 682236.9222659998,
          "liquidity": 278497.05094,
          "active": true,
          "closed": false,
          "end_date": "2026-05-31T00:00:00Z",
          "status": "ok"
        },
        {
          "source": "polymarket",
          "id": "558937",
          "question": "Will Brazil win the 2026 FIFA World Cup?",
          "slug": "will-brazil-win-the-2026-fifa-world-cup-183",
          "market_type": "binary",
          "yes_price": 0.085,
          "no_price": 0.915,
          "outcomes": [
            "Yes",
            "No"
          ],
          "outcome_prices": [
            0.085,
            0.915
          ],
          "volume_24h": 660961.754704,
          "liquidity": 1782711.36902,
          "active": true,
          "closed": false,
          "end_date": "2026-07-20T00:00:00Z",
          "status": "ok"
        }
      ],
      "errors": []
    },
    "google_trends": {
      "status": "partial",
      "meta": {
        "timeframe": "now 1-d",
        "geo": "global",
        "anchor_keyword": "Federal Reserve"
      },
      "summary": {
        "anchor_keyword": "Federal Reserve",
        "total_rows": 14,
        "top_keywords_by_anchor_normalized_mean_24h": []
      },
      "data": [
        {
          "source": "google_trends",
          "keyword": "Iran war",
          "anchor_keyword": "Federal Reserve",
          "chunk_index": 0,
          "score_mean_24h_raw": null,
          "score_last_raw": null,
          "anchor_mean_24h_raw": null,
          "anchor_last_raw": null,
          "score_mean_24h_anchor_normalized": null,
          "score_last_anchor_normalized": null,
          "status": "error",
          "error": "The request failed: Google returned a response with code 429",
          "notes": "Chunk-level request failed."
        },
        {
          "source": "google_trends",
          "keyword": "Ukraine war",
          "anchor_keyword": "Federal Reserve",
          "chunk_index": 0,
          "score_mean_24h_raw": null,
          "score_last_raw": null,
          "anchor_mean_24h_raw": null,
          "anchor_last_raw": null,
          "score_mean_24h_anchor_normalized": null,
          "score_last_anchor_normalized": null,
          "status": "error",
          "error": "The request failed: Google returned a response with code 429",
          "notes": "Chunk-level request failed."
        },
        {
          "source": "google_trends",
          "keyword": "NATO",
          "anchor_keyword": "Federal Reserve",
          "chunk_index": 0,
          "score_mean_24h_raw": null,
          "score_last_raw": null,
          "anchor_mean_24h_raw": null,
          "anchor_last_raw": null,
          "score_mean_24h_anchor_normalized": null,
          "score_last_anchor_normalized": null,
          "status": "error",
          "error": "The request failed: Google returned a response with code 429",
          "notes": "Chunk-level request failed."
        },
        {
          "source": "google_trends",
          "keyword": "oil price",
          "anchor_keyword": "Federal Reserve",
          "chunk_index": 0,
          "score_mean_24h_raw": null,
          "score_last_raw": null,
          "anchor_mean_24h_raw": null,
          "anchor_last_raw": null,
          "score_mean_24h_anchor_normalized": null,
          "score_last_anchor_normalized": null,
          "status": "error",
          "error": "The request failed: Google returned a response with code 429",
          "notes": "Chunk-level request failed."
        },
        {
          "source": "google_trends",
          "keyword": "gold price",
          "anchor_keyword": "Federal Reserve",
          "chunk_index": 1,
          "score_mean_24h_raw": null,
          "score_last_raw": null,
          "anchor_mean_24h_raw": null,
          "anchor_last_raw": null,
          "score_mean_24h_anchor_normalized": null,
          "score_last_anchor_normalized": null,
          "status": "error",
          "error": "The request failed: Google returned a response with code 429",
          "notes": "Chunk-level request failed."
        },
        {
          "source": "google_trends",
          "keyword": "recession",
          "anchor_keyword": "Federal Reserve",
          "chunk_index": 1,
          "score_mean_24h_raw": null,
          "score_last_raw": null,
          "anchor_mean_24h_raw": null,
          "anchor_last_raw": null,
          "score_mean_24h_anchor_normalized": null,
          "score_last_anchor_normalized": null,
          "status": "error",
          "error": "The request failed: Google returned a response with code 429",
          "notes": "Chunk-level request failed."
        },
        {
          "source": "google_trends",
          "keyword": "Trump tariffs",
          "anchor_keyword": "Federal Reserve",
          "chunk_index": 1,
          "score_mean_24h_raw": null,
          "score_last_raw": null,
          "anchor_mean_24h_raw": null,
          "anchor_last_raw": null,
          "score_mean_24h_anchor_normalized": null,
          "score_last_anchor_normalized": null,
          "status": "error",
          "error": "The request failed: Google returned a response with code 429",
          "notes": "Chunk-level request failed."
        },
        {
          "source": "google_trends",
          "keyword": "interest rate",
          "anchor_keyword": "Federal Reserve",
          "chunk_index": 1,
          "score_mean_24h_raw": null,
          "score_last_raw": null,
          "anchor_mean_24h_raw": null,
          "anchor_last_raw": null,
          "score_mean_24h_anchor_normalized": null,
          "score_last_anchor_normalized": null,
          "status": "error",
          "error": "The request failed: Google returned a response with code 429",
          "notes": "Chunk-level request failed."
        },
        {
          "source": "google_trends",
          "keyword": "inflation",
          "anchor_keyword": "Federal Reserve",
          "chunk_index": 2,
          "score_mean_24h_raw": null,
          "score_last_raw": null,
          "anchor_mean_24h_raw": null,
          "anchor_last_raw": null,
          "score_mean_24h_anchor_normalized": null,
          "score_last_anchor_normalized": null,
          "status": "error",
          "error": "The request failed: Google returned a response with code 429",
          "notes": "Chunk-level request failed."
        },
        {
          "source": "google_trends",
          "keyword": "AI regulation",
          "anchor_keyword": "Federal Reserve",
          "chunk_index": 2,
          "score_mean_24h_raw": null,
          "score_last_raw": null,
          "anchor_mean_24h_raw": null,
          "anchor_last_raw": null,
          "score_mean_24h_anchor_normalized": null,
          "score_last_anchor_normalized": null,
          "status": "error",
          "error": "The request failed: Google returned a response with code 429",
          "notes": "Chunk-level request failed."
        },
        {
          "source": "google_trends",
          "keyword": "chip export",
          "anchor_keyword": "Federal Reserve",
          "chunk_index": 2,
          "score_mean_24h_raw": null,
          "score_last_raw": null,
          "anchor_mean_24h_raw": null,
          "anchor_last_raw": null,
          "score_mean_24h_anchor_normalized": null,
          "score_last_anchor_normalized": null,
          "status": "error",
          "error": "The request failed: Google returned a response with code 429",
          "notes": "Chunk-level request failed."
        },
        {
          "source": "google_trends",
          "keyword": "China economy",
          "anchor_keyword": "Federal Reserve",
          "chunk_index": 2,
          "score_mean_24h_raw": null,
          "score_last_raw": null,
          "anchor_mean_24h_raw": null,
          "anchor_last_raw": null,
          "score_mean_24h_anchor_normalized": null,
          "score_last_anchor_normalized": null,
          "status": "error",
          "error": "The request failed: Google returned a response with code 429",
          "notes": "Chunk-level request failed."
        },
        {
          "source": "google_trends",
          "keyword": "China US",
          "anchor_keyword": "Federal Reserve",
          "chunk_index": 3,
          "score_mean_24h_raw": null,
          "score_last_raw": null,
          "anchor_mean_24h_raw": null,
          "anchor_last_raw": null,
          "score_mean_24h_anchor_normalized": null,
          "score_last_anchor_normalized": null,
          "status": "error",
          "error": "The request failed: Google returned a response with code 429",
          "notes": "Chunk-level request failed."
        },
        {
          "source": "google_trends",
          "keyword": "OPEC",
          "anchor_keyword": "Federal Reserve",
          "chunk_index": 3,
          "score_mean_24h_raw": null,
          "score_last_raw": null,
          "anchor_mean_24h_raw": null,
          "anchor_last_raw": null,
          "score_mean_24h_anchor_normalized": null,
          "score_last_anchor_normalized": null,
          "status": "error",
          "error": "The request failed: Google returned a response with code 429",
          "notes": "Chunk-level request failed."
        }
      ],
      "errors": [
        {
          "source": "google_trends",
          "chunk_index": 0,
          "chunk": [
            "Iran war",
            "Ukraine war",
            "NATO",
            "oil price",
            "Federal Reserve"
          ],
          "status": "error",
          "error_type": "TooManyRequestsError",
          "message": "The request failed: Google returned a response with code 429"
        },
        {
          "source": "google_trends",
          "chunk_index": 1,
          "chunk": [
            "gold price",
            "recession",
            "Trump tariffs",
            "interest rate",
            "Federal Reserve"
          ],
          "status": "error",
          "error_type": "TooManyRequestsError",
          "message": "The request failed: Google returned a response with code 429"
        },
        {
          "source": "google_trends",
          "chunk_index": 2,
          "chunk": [
            "inflation",
            "AI regulation",
            "chip export",
            "China economy",
            "Federal Reserve"
          ],
          "status": "error",
          "error_type": "TooManyRequestsError",
          "message": "The request failed: Google returned a response with code 429"
        },
        {
          "source": "google_trends",
          "chunk_index": 3,
          "chunk": [
            "China US",
            "OPEC",
            "Federal Reserve"
          ],
          "status": "error",
          "error_type": "TooManyRequestsError",
          "message": "The request failed: Google returned a response with code 429"
        }
      ]
    },
    "wikipedia_pageviews": {
      "status": "ok",
      "meta": {
        "date": "20260421"
      },
      "summary": {
        "date": "20260421",
        "total_rows": 10,
        "top_pages_by_views": [
          {
            "page": "Kevin_Warsh",
            "views": 98968
          },
          {
            "page": "Donald_Trump",
            "views": 59125
          },
          {
            "page": "Strait_of_Hormuz",
            "views": 22824
          },
          {
            "page": "NATO",
            "views": 6708
          },
          {
            "page": "Russo-Ukrainian_War",
            "views": 2964
          }
        ]
      },
      "data": [
        {
          "source": "wikipedia_pageviews",
          "page": "Strait_of_Hormuz",
          "date": "20260421",
          "views": 22824,
          "status": "ok",
          "error": null
        },
        {
          "source": "wikipedia_pageviews",
          "page": "Russo-Ukrainian_War",
          "date": "20260421",
          "views": 2964,
          "status": "ok",
          "error": null
        },
        {
          "source": "wikipedia_pageviews",
          "page": "Federal_Reserve",
          "date": "20260421",
          "views": 2675,
          "status": "ok",
          "error": null
        },
        {
          "source": "wikipedia_pageviews",
          "page": "Donald_Trump",
          "date": "20260421",
          "views": 59125,
          "status": "ok",
          "error": null
        },
        {
          "source": "wikipedia_pageviews",
          "page": "OPEC",
          "date": "20260421",
          "views": 1771,
          "status": "ok",
          "error": null
        },
        {
          "source": "wikipedia_pageviews",
          "page": "NATO",
          "date": "20260421",
          "views": 6708,
          "status": "ok",
          "error": null
        },
        {
          "source": "wikipedia_pageviews",
          "page": "Artificial_intelligence_regulation",
          "date": "20260421",
          "views": 9,
          "status": "ok",
          "error": null
        },
        {
          "source": "wikipedia_pageviews",
          "page": "Kevin_Warsh",
          "date": "20260421",
          "views": 98968,
          "status": "ok",
          "error": null
        },
        {
          "source": "wikipedia_pageviews",
          "page": "China%E2%80%93United_States_trade_war",
          "date": "20260421",
          "views": 1110,
          "status": "ok",
          "error": null
        },
        {
          "source": "wikipedia_pageviews",
          "page": "Semiconductor",
          "date": "20260421",
          "views": 1450,
          "status": "ok",
          "error": null
        }
      ],
      "errors": []
    }
  },
  "delta_vs_previous_day": {
    "available": true,
    "previous_date_utc": "2026-04-22",
    "current_date_utc": "2026-04-22",
    "comparison_type": "same_day_rerun",
    "sources": {
      "polymarket": {
        "comparison_key": "question",
        "row_count": 30,
        "data": [
          {
            "question": "Will Bitcoin hit $150k by June 30, 2026?",
            "market_type": "binary",
            "volume_24h_delta": {
              "current": 5821652.894196,
              "previous": 5821652.894196,
              "absolute_change": 0.0,
              "pct_change": 0.0,
              "direction": "flat"
            },
            "yes_price_delta": {
              "current": 0.0135,
              "previous": 0.0135,
              "absolute_change": 0.0,
              "pct_change": 0.0,
              "direction": "flat"
            },
            "is_new_market_vs_previous": false
          },
          {
            "question": "US x Iran permanent peace deal by April 22, 2026?",
            "market_type": "binary",
            "volume_24h_delta": {
              "current": 5520100.854613998,
              "previous": 5469523.040071993,
              "absolute_change": 50577.8145,
              "pct_change": 0.92,
              "direction": "up"
            },
            "yes_price_delta": {
              "current": 0.019,
              "previous": 0.0045,
              "absolute_change": 0.0145,
              "pct_change": 322.22,
              "direction": "up"
            },
            "is_new_market_vs_previous": false
          },
          {
            "question": "Iran x Israel/US conflict ends by April 7?",
            "market_type": "binary",
            "volume_24h_delta": {
              "current": 4328200.489911007,
              "previous": 4210733.991563004,
              "absolute_change": 117466.4983,
              "pct_change": 2.79,
              "direction": "up"
            },
            "yes_price_delta": {
              "current": 0.9975,
              "previous": 0.9975,
              "absolute_change": 0.0,
              "pct_change": 0.0,
              "direction": "flat"
            },
            "is_new_market_vs_previous": false
          },
          {
            "question": "Strait of Hormuz traffic returns to normal by end of April?",
            "market_type": "binary",
            "volume_24h_delta": {
              "current": 2971417.5243400005,
              "previous": 3044779.3523959913,
              "absolute_change": -73361.8281,
              "pct_change": -2.41,
              "direction": "down"
            },
            "yes_price_delta": {
              "current": 0.115,
              "previous": 0.095,
              "absolute_change": 0.02,
              "pct_change": 21.05,
              "direction": "up"
            },
            "is_new_market_vs_previous": false
          },
          {
            "question": "Iran x Israel/US conflict ends by May 15?",
            "market_type": "binary",
            "volume_24h_delta": {
              "current": 2596399.589361,
              "previous": 2577904.8971309992,
              "absolute_change": 18494.6922,
              "pct_change": 0.72,
              "direction": "up"
            },
            "yes_price_delta": {
              "current": 0.9985,
              "previous": 0.9985,
              "absolute_change": 0.0,
              "pct_change": 0.0,
              "direction": "flat"
            },
            "is_new_market_vs_previous": false
          },
          {
            "question": "Iran x Israel/US conflict ends by April 15?",
            "market_type": "binary",
            "volume_24h_delta": {
              "current": 2326530.241561997,
              "previous": 2327121.803046997,
              "absolute_change": -591.5615,
              "pct_change": -0.03,
              "direction": "down"
            },
            "yes_price_delta": {
              "current": 0.9975,
              "previous": 0.9975,
              "absolute_change": 0.0,
              "pct_change": 0.0,
              "direction": "flat"
            },
            "is_new_market_vs_previous": false
          },
          {
            "question": "Will there be no change in Fed interest rates after the April 2026 meeting?",
            "market_type": "binary",
            "volume_24h_delta": {
              "current": 2209434.762801,
              "previous": 2251516.657558001,
              "absolute_change": -42081.8948,
              "pct_change": -1.87,
              "direction": "down"
            },
            "yes_price_delta": {
              "current": 0.9935,
              "previous": 0.9935,
              "absolute_change": 0.0,
              "pct_change": 0.0,
              "direction": "flat"
            },
            "is_new_market_vs_previous": false
          },
          {
            "question": "US x Iran permanent peace deal by April 30, 2026?",
            "market_type": "binary",
            "volume_24h_delta": {
              "current": 2137958.7420779946,
              "previous": 2152453.516424996,
              "absolute_change": -14494.7743,
              "pct_change": -0.67,
              "direction": "down"
            },
            "yes_price_delta": {
              "current": 0.145,
              "previous": 0.145,
              "absolute_change": 0.0,
              "pct_change": 0.0,
              "direction": "flat"
            },
            "is_new_market_vs_previous": false
          },
          {
            "question": "Will USA win the 2026 FIFA World Cup?",
            "market_type": "binary",
            "volume_24h_delta": {
              "current": 2077136.6515020004,
              "previous": 2258317.920426,
              "absolute_change": -181181.2689,
              "pct_change": -8.02,
              "direction": "down"
            },
            "yes_price_delta": {
              "current": 0.0125,
              "previous": 0.0125,
              "absolute_change": 0.0,
              "pct_change": 0.0,
              "direction": "flat"
            },
            "is_new_market_vs_previous": false
          },
          {
            "question": "Will the U.S. invade Iran before 2027?",
            "market_type": "binary",
            "volume_24h_delta": {
              "current": 2030660.8604640327,
              "previous": 2002982.3931340326,
              "absolute_change": 27678.4673,
              "pct_change": 1.38,
              "direction": "up"
            },
            "yes_price_delta": {
              "current": 0.305,
              "previous": 0.305,
              "absolute_change": 0.0,
              "pct_change": 0.0,
              "direction": "flat"
            },
            "is_new_market_vs_previous": false
          },
          {
            "question": "Iran x Israel/US conflict ends by June 30?",
            "market_type": "binary",
            "volume_24h_delta": {
              "current": 1437826.4901630008,
              "previous": 1424965.6971040007,
              "absolute_change": 12860.7931,
              "pct_change": 0.9,
              "direction": "up"
            },
            "yes_price_delta": {
              "current": 0.9985,
              "previous": 0.9985,
              "absolute_change": 0.0,
              "pct_change": 0.0,
              "direction": "flat"
            },
            "is_new_market_vs_previous": false
          },
          {
            "question": "Will the Iranian regime fall by April 30?",
            "market_type": "binary",
            "volume_24h_delta": {
              "current": 1278320.0068060004,
              "previous": 1338330.3658340005,
              "absolute_change": -60010.359,
              "pct_change": -4.48,
              "direction": "down"
            },
            "yes_price_delta": {
              "current": 0.0055,
              "previous": 0.0065,
              "absolute_change": -0.001,
              "pct_change": -15.38,
              "direction": "down"
            },
            "is_new_market_vs_previous": false
          },
          {
            "question": "US x Iran diplomatic meeting by April 22, 2026?",
            "market_type": "binary",
            "volume_24h_delta": {
              "current": 1237573.2409640076,
              "previous": 1288510.5134150074,
              "absolute_change": -50937.2725,
              "pct_change": -3.95,
              "direction": "down"
            },
            "yes_price_delta": {
              "current": 0.0055,
              "previous": 0.01,
              "absolute_change": -0.0045,
              "pct_change": -45.0,
              "direction": "down"
            },
            "is_new_market_vs_previous": false
          },
          {
            "question": "Will the Fed decrease interest rates by 25 bps after the April 2026 meeting?",
            "market_type": "binary",
            "volume_24h_delta": {
              "current": 1145117.876309999,
              "previous": 1162899.2619749992,
              "absolute_change": -17781.3857,
              "pct_change": -1.53,
              "direction": "down"
            },
            "yes_price_delta": {
              "current": 0.0025,
              "previous": 0.0025,
              "absolute_change": 0.0,
              "pct_change": 0.0,
              "direction": "flat"
            },
            "is_new_market_vs_previous": false
          },
          {
            "question": "Will the Boston Celtics win the 2026 NBA Finals?",
            "market_type": "binary",
            "volume_24h_delta": {
              "current": 1113312.8496100002,
              "previous": 1057966.8337480002,
              "absolute_change": 55346.0159,
              "pct_change": 5.23,
              "direction": "up"
            },
            "yes_price_delta": {
              "current": 0.121,
              "previous": 0.12,
              "absolute_change": 0.001,
              "pct_change": 0.83,
              "direction": "up"
            },
            "is_new_market_vs_previous": false
          },
          {
            "question": "LoL: KT Rolster vs Kiwoom DRX - Game 1 Winner",
            "market_type": "non_binary",
            "volume_24h_delta": {
              "current": 1077963.6831820002,
              "previous": null,
              "absolute_change": null,
              "pct_change": null,
              "direction": "unknown"
            },
            "yes_price_delta": {
              "current": null,
              "previous": null,
              "absolute_change": null,
              "pct_change": null,
              "direction": "unknown"
            },
            "is_new_market_vs_previous": true
          },
          {
            "question": "Will Czechia win the 2026 FIFA World Cup?",
            "market_type": "binary",
            "volume_24h_delta": {
              "current": 1043742.8634799999,
              "previous": 1045994.6351429999,
              "absolute_change": -2251.7717,
              "pct_change": -0.22,
              "direction": "down"
            },
            "yes_price_delta": {
              "current": 0.0025,
              "previous": 0.0025,
              "absolute_change": 0.0,
              "pct_change": 0.0,
              "direction": "flat"
            },
            "is_new_market_vs_previous": false
          },
          {
            "question": "Will Roberto Sánchez Palomino win the 2026 Peruvian presidential election?",
            "market_type": "binary",
            "volume_24h_delta": {
              "current": 1024862.419367,
              "previous": 953238.611418,
              "absolute_change": 71623.8079,
              "pct_change": 7.51,
              "direction": "up"
            },
            "yes_price_delta": {
              "current": 0.2345,
              "previous": 0.238,
              "absolute_change": -0.0035,
              "pct_change": -1.47,
              "direction": "down"
            },
            "is_new_market_vs_previous": false
          },
          {
            "question": "Will the San Antonio Spurs win the 2026 NBA Finals?",
            "market_type": "binary",
            "volume_24h_delta": {
              "current": 1019839.1687049998,
              "previous": 996555.6357220002,
              "absolute_change": 23283.533,
              "pct_change": 2.34,
              "direction": "up"
            },
            "yes_price_delta": {
              "current": 0.121,
              "previous": 0.1225,
              "absolute_change": -0.0015,
              "pct_change": -1.22,
              "direction": "down"
            },
            "is_new_market_vs_previous": false
          },
          {
            "question": "Kharg Island no longer under Iranian control by April 30?",
            "market_type": "binary",
            "volume_24h_delta": {
              "current": 943207.8064029993,
              "previous": 904355.1094349991,
              "absolute_change": 38852.697,
              "pct_change": 4.3,
              "direction": "up"
            },
            "yes_price_delta": {
              "current": 0.073,
              "previous": 0.0625,
              "absolute_change": 0.0105,
              "pct_change": 16.8,
              "direction": "up"
            },
            "is_new_market_vs_previous": false
          },
          {
            "question": "US x Iran ceasefire extended by April 22, 2026?",
            "market_type": "binary",
            "volume_24h_delta": {
              "current": 930661.1129820021,
              "previous": 872334.004452002,
              "absolute_change": 58327.1085,
              "pct_change": 6.69,
              "direction": "up"
            },
            "yes_price_delta": {
              "current": 0.135,
              "previous": 0.16,
              "absolute_change": -0.025,
              "pct_change": -15.62,
              "direction": "down"
            },
            "is_new_market_vs_previous": false
          },
          {
            "question": "Will the Fed decrease interest rates by 50+ bps after the April 2026 meeting?",
            "market_type": "binary",
            "volume_24h_delta": {
              "current": 912987.1700000009,
              "previous": 937482.1130000006,
              "absolute_change": -24494.943,
              "pct_change": -2.61,
              "direction": "down"
            },
            "yes_price_delta": {
              "current": 0.0015,
              "previous": 0.0015,
              "absolute_change": 0.0,
              "pct_change": 0.0,
              "direction": "flat"
            },
            "is_new_market_vs_previous": false
          },
          {
            "question": "Will the Fed increase interest rates by 25+ bps after the April 2026 meeting?",
            "market_type": "binary",
            "volume_24h_delta": {
              "current": 879177.9238060002,
              "previous": 873584.0026400002,
              "absolute_change": 5593.9212,
              "pct_change": 0.64,
              "direction": "up"
            },
            "yes_price_delta": {
              "current": 0.0025,
              "previous": 0.0025,
              "absolute_change": 0.0,
              "pct_change": 0.0,
              "direction": "flat"
            },
            "is_new_market_vs_previous": false
          },
          {
            "question": "Trump out as President by April 30?",
            "market_type": "binary",
            "volume_24h_delta": {
              "current": 853659.4391800003,
              "previous": 790889.4101140001,
              "absolute_change": 62770.0291,
              "pct_change": 7.94,
              "direction": "up"
            },
            "yes_price_delta": {
              "current": 0.0045,
              "previous": 0.0065,
              "absolute_change": -0.002,
              "pct_change": -30.77,
              "direction": "down"
            },
            "is_new_market_vs_previous": false
          },
          {
            "question": "Will the Philadelphia 76ers win the 2026 NBA Finals?",
            "market_type": "binary",
            "volume_24h_delta": {
              "current": 816510.9503829998,
              "previous": 818479.9666329997,
              "absolute_change": -1969.0162,
              "pct_change": -0.24,
              "direction": "down"
            },
            "yes_price_delta": {
              "current": 0.0045,
              "previous": 0.0045,
              "absolute_change": 0.0,
              "pct_change": 0.0,
              "direction": "flat"
            },
            "is_new_market_vs_previous": false
          },
          {
            "question": "Will Kevin Warsh be confirmed as Fed Chair?",
            "market_type": "binary",
            "volume_24h_delta": {
              "current": 778429.3443509992,
              "previous": 742055.8396930001,
              "absolute_change": 36373.5047,
              "pct_change": 4.9,
              "direction": "up"
            },
            "yes_price_delta": {
              "current": 0.943,
              "previous": 0.9435,
              "absolute_change": -0.0005,
              "pct_change": -0.05,
              "direction": "down"
            },
            "is_new_market_vs_previous": false
          },
          {
            "question": "Dota 2: GamerLegion vs Heroic - Game 1 Winner",
            "market_type": "non_binary",
            "volume_24h_delta": {
              "current": 729553.2982359976,
              "previous": null,
              "absolute_change": null,
              "pct_change": null,
              "direction": "unknown"
            },
            "yes_price_delta": {
              "current": null,
              "previous": null,
              "absolute_change": null,
              "pct_change": null,
              "direction": "unknown"
            },
            "is_new_market_vs_previous": true
          },
          {
            "question": "Will the Portland Trail Blazers win the 2026 NBA Finals?",
            "market_type": "binary",
            "volume_24h_delta": {
              "current": 684106.1444620002,
              "previous": 649796.235987,
              "absolute_change": 34309.9085,
              "pct_change": 5.28,
              "direction": "up"
            },
            "yes_price_delta": {
              "current": 0.0045,
              "previous": 0.0035,
              "absolute_change": 0.001,
              "pct_change": 28.57,
              "direction": "up"
            },
            "is_new_market_vs_previous": false
          },
          {
            "question": "Will the Iranian regime fall by May 31?",
            "market_type": "binary",
            "volume_24h_delta": {
              "current": 682236.9222659998,
              "previous": null,
              "absolute_change": null,
              "pct_change": null,
              "direction": "unknown"
            },
            "yes_price_delta": {
              "current": 0.047,
              "previous": null,
              "absolute_change": null,
              "pct_change": null,
              "direction": "unknown"
            },
            "is_new_market_vs_previous": true
          },
          {
            "question": "Will Brazil win the 2026 FIFA World Cup?",
            "market_type": "binary",
            "volume_24h_delta": {
              "current": 660961.754704,
              "previous": 614380.9960399998,
              "absolute_change": 46580.7587,
              "pct_change": 7.58,
              "direction": "up"
            },
            "yes_price_delta": {
              "current": 0.085,
              "previous": 0.085,
              "absolute_change": 0.0,
              "pct_change": 0.0,
              "direction": "flat"
            },
            "is_new_market_vs_previous": false
          }
        ],
        "summary": {
          "top_volume_risers": [
            {
              "question": "Iran x Israel/US conflict ends by April 7?",
              "absolute_change": 117466.4983,
              "pct_change": 2.79
            },
            {
              "question": "Will Roberto Sánchez Palomino win the 2026 Peruvian presidential election?",
              "absolute_change": 71623.8079,
              "pct_change": 7.51
            },
            {
              "question": "Trump out as President by April 30?",
              "absolute_change": 62770.0291,
              "pct_change": 7.94
            },
            {
              "question": "US x Iran ceasefire extended by April 22, 2026?",
              "absolute_change": 58327.1085,
              "pct_change": 6.69
            },
            {
              "question": "Will the Boston Celtics win the 2026 NBA Finals?",
              "absolute_change": 55346.0159,
              "pct_change": 5.23
            }
          ],
          "top_volume_fallers": [
            {
              "question": "Will USA win the 2026 FIFA World Cup?",
              "absolute_change": -181181.2689,
              "pct_change": -8.02
            },
            {
              "question": "Strait of Hormuz traffic returns to normal by end of April?",
              "absolute_change": -73361.8281,
              "pct_change": -2.41
            },
            {
              "question": "Will the Iranian regime fall by April 30?",
              "absolute_change": -60010.359,
              "pct_change": -4.48
            },
            {
              "question": "US x Iran diplomatic meeting by April 22, 2026?",
              "absolute_change": -50937.2725,
              "pct_change": -3.95
            },
            {
              "question": "Will there be no change in Fed interest rates after the April 2026 meeting?",
              "absolute_change": -42081.8948,
              "pct_change": -1.87
            }
          ],
          "new_markets_vs_previous": 3
        }
      },
      "google_trends": {
        "comparison_key": "keyword",
        "row_count": 14,
        "data": [
          {
            "keyword": "Iran war",
            "mean_anchor_normalized_delta": {
              "current": null,
              "previous": null,
              "absolute_change": null,
              "pct_change": null,
              "direction": "unknown"
            },
            "last_anchor_normalized_delta": {
              "current": null,
              "previous": null,
              "absolute_change": null,
              "pct_change": null,
              "direction": "unknown"
            },
            "is_new_keyword_vs_previous": false
          },
          {
            "keyword": "Ukraine war",
            "mean_anchor_normalized_delta": {
              "current": null,
              "previous": null,
              "absolute_change": null,
              "pct_change": null,
              "direction": "unknown"
            },
            "last_anchor_normalized_delta": {
              "current": null,
              "previous": null,
              "absolute_change": null,
              "pct_change": null,
              "direction": "unknown"
            },
            "is_new_keyword_vs_previous": false
          },
          {
            "keyword": "NATO",
            "mean_anchor_normalized_delta": {
              "current": null,
              "previous": null,
              "absolute_change": null,
              "pct_change": null,
              "direction": "unknown"
            },
            "last_anchor_normalized_delta": {
              "current": null,
              "previous": null,
              "absolute_change": null,
              "pct_change": null,
              "direction": "unknown"
            },
            "is_new_keyword_vs_previous": false
          },
          {
            "keyword": "oil price",
            "mean_anchor_normalized_delta": {
              "current": null,
              "previous": null,
              "absolute_change": null,
              "pct_change": null,
              "direction": "unknown"
            },
            "last_anchor_normalized_delta": {
              "current": null,
              "previous": null,
              "absolute_change": null,
              "pct_change": null,
              "direction": "unknown"
            },
            "is_new_keyword_vs_previous": false
          },
          {
            "keyword": "gold price",
            "mean_anchor_normalized_delta": {
              "current": null,
              "previous": null,
              "absolute_change": null,
              "pct_change": null,
              "direction": "unknown"
            },
            "last_anchor_normalized_delta": {
              "current": null,
              "previous": null,
              "absolute_change": null,
              "pct_change": null,
              "direction": "unknown"
            },
            "is_new_keyword_vs_previous": false
          },
          {
            "keyword": "recession",
            "mean_anchor_normalized_delta": {
              "current": null,
              "previous": null,
              "absolute_change": null,
              "pct_change": null,
              "direction": "unknown"
            },
            "last_anchor_normalized_delta": {
              "current": null,
              "previous": null,
              "absolute_change": null,
              "pct_change": null,
              "direction": "unknown"
            },
            "is_new_keyword_vs_previous": false
          },
          {
            "keyword": "Trump tariffs",
            "mean_anchor_normalized_delta": {
              "current": null,
              "previous": null,
              "absolute_change": null,
              "pct_change": null,
              "direction": "unknown"
            },
            "last_anchor_normalized_delta": {
              "current": null,
              "previous": null,
              "absolute_change": null,
              "pct_change": null,
              "direction": "unknown"
            },
            "is_new_keyword_vs_previous": false
          },
          {
            "keyword": "interest rate",
            "mean_anchor_normalized_delta": {
              "current": null,
              "previous": null,
              "absolute_change": null,
              "pct_change": null,
              "direction": "unknown"
            },
            "last_anchor_normalized_delta": {
              "current": null,
              "previous": null,
              "absolute_change": null,
              "pct_change": null,
              "direction": "unknown"
            },
            "is_new_keyword_vs_previous": false
          },
          {
            "keyword": "inflation",
            "mean_anchor_normalized_delta": {
              "current": null,
              "previous": null,
              "absolute_change": null,
              "pct_change": null,
              "direction": "unknown"
            },
            "last_anchor_normalized_delta": {
              "current": null,
              "previous": null,
              "absolute_change": null,
              "pct_change": null,
              "direction": "unknown"
            },
            "is_new_keyword_vs_previous": false
          },
          {
            "keyword": "AI regulation",
            "mean_anchor_normalized_delta": {
              "current": null,
              "previous": null,
              "absolute_change": null,
              "pct_change": null,
              "direction": "unknown"
            },
            "last_anchor_normalized_delta": {
              "current": null,
              "previous": null,
              "absolute_change": null,
              "pct_change": null,
              "direction": "unknown"
            },
            "is_new_keyword_vs_previous": false
          },
          {
            "keyword": "chip export",
            "mean_anchor_normalized_delta": {
              "current": null,
              "previous": null,
              "absolute_change": null,
              "pct_change": null,
              "direction": "unknown"
            },
            "last_anchor_normalized_delta": {
              "current": null,
              "previous": null,
              "absolute_change": null,
              "pct_change": null,
              "direction": "unknown"
            },
            "is_new_keyword_vs_previous": false
          },
          {
            "keyword": "China economy",
            "mean_anchor_normalized_delta": {
              "current": null,
              "previous": null,
              "absolute_change": null,
              "pct_change": null,
              "direction": "unknown"
            },
            "last_anchor_normalized_delta": {
              "current": null,
              "previous": null,
              "absolute_change": null,
              "pct_change": null,
              "direction": "unknown"
            },
            "is_new_keyword_vs_previous": false
          },
          {
            "keyword": "China US",
            "mean_anchor_normalized_delta": {
              "current": null,
              "previous": null,
              "absolute_change": null,
              "pct_change": null,
              "direction": "unknown"
            },
            "last_anchor_normalized_delta": {
              "current": null,
              "previous": null,
              "absolute_change": null,
              "pct_change": null,
              "direction": "unknown"
            },
            "is_new_keyword_vs_previous": false
          },
          {
            "keyword": "OPEC",
            "mean_anchor_normalized_delta": {
              "current": null,
              "previous": null,
              "absolute_change": null,
              "pct_change": null,
              "direction": "unknown"
            },
            "last_anchor_normalized_delta": {
              "current": null,
              "previous": null,
              "absolute_change": null,
              "pct_change": null,
              "direction": "unknown"
            },
            "is_new_keyword_vs_previous": false
          }
        ],
        "summary": {
          "top_risers": [],
          "top_fallers": [],
          "new_keywords_vs_previous": 0
        }
      },
      "wikipedia_pageviews": {
        "comparison_key": "page",
        "row_count": 10,
        "data": [
          {
            "page": "Strait_of_Hormuz",
            "views_delta": {
              "current": 22824,
              "previous": 22824,
              "absolute_change": 0,
              "pct_change": 0.0,
              "direction": "flat"
            },
            "is_new_page_vs_previous": false
          },
          {
            "page": "Russo-Ukrainian_War",
            "views_delta": {
              "current": 2964,
              "previous": 2964,
              "absolute_change": 0,
              "pct_change": 0.0,
              "direction": "flat"
            },
            "is_new_page_vs_previous": false
          },
          {
            "page": "Federal_Reserve",
            "views_delta": {
              "current": 2675,
              "previous": 2675,
              "absolute_change": 0,
              "pct_change": 0.0,
              "direction": "flat"
            },
            "is_new_page_vs_previous": false
          },
          {
            "page": "Donald_Trump",
            "views_delta": {
              "current": 59125,
              "previous": 59125,
              "absolute_change": 0,
              "pct_change": 0.0,
              "direction": "flat"
            },
            "is_new_page_vs_previous": false
          },
          {
            "page": "OPEC",
            "views_delta": {
              "current": 1771,
              "previous": 1771,
              "absolute_change": 0,
              "pct_change": 0.0,
              "direction": "flat"
            },
            "is_new_page_vs_previous": false
          },
          {
            "page": "NATO",
            "views_delta": {
              "current": 6708,
              "previous": 6708,
              "absolute_change": 0,
              "pct_change": 0.0,
              "direction": "flat"
            },
            "is_new_page_vs_previous": false
          },
          {
            "page": "Artificial_intelligence_regulation",
            "views_delta": {
              "current": 9,
              "previous": 9,
              "absolute_change": 0,
              "pct_change": 0.0,
              "direction": "flat"
            },
            "is_new_page_vs_previous": false
          },
          {
            "page": "Kevin_Warsh",
            "views_delta": {
              "current": 98968,
              "previous": 98968,
              "absolute_change": 0,
              "pct_change": 0.0,
              "direction": "flat"
            },
            "is_new_page_vs_previous": false
          },
          {
            "page": "China%E2%80%93United_States_trade_war",
            "views_delta": {
              "current": 1110,
              "previous": 1110,
              "absolute_change": 0,
              "pct_change": 0.0,
              "direction": "flat"
            },
            "is_new_page_vs_previous": false
          },
          {
            "page": "Semiconductor",
            "views_delta": {
              "current": 1450,
              "previous": 1450,
              "absolute_change": 0,
              "pct_change": 0.0,
              "direction": "flat"
            },
            "is_new_page_vs_previous": false
          }
        ],
        "summary": {
          "top_risers": [
            {
              "page": "Strait_of_Hormuz",
              "absolute_change": 0,
              "pct_change": 0.0
            },
            {
              "page": "Russo-Ukrainian_War",
              "absolute_change": 0,
              "pct_change": 0.0
            },
            {
              "page": "Federal_Reserve",
              "absolute_change": 0,
              "pct_change": 0.0
            },
            {
              "page": "Donald_Trump",
              "absolute_change": 0,
              "pct_change": 0.0
            },
            {
              "page": "OPEC",
              "absolute_change": 0,
              "pct_change": 0.0
            }
          ],
          "top_fallers": [
            {
              "page": "Strait_of_Hormuz",
              "absolute_change": 0,
              "pct_change": 0.0
            },
            {
              "page": "Russo-Ukrainian_War",
              "absolute_change": 0,
              "pct_change": 0.0
            },
            {
              "page": "Federal_Reserve",
              "absolute_change": 0,
              "pct_change": 0.0
            },
            {
              "page": "Donald_Trump",
              "absolute_change": 0,
              "pct_change": 0.0
            },
            {
              "page": "OPEC",
              "absolute_change": 0,
              "pct_change": 0.0
            }
          ],
          "new_pages_vs_previous": 0
        }
      }
    },
    "summary": {
      "notes": [
        "Comparison is against the previously committed output file in the repo.",
        "If the workflow is re-run on the same UTC date, comparison_type may be same_day_rerun instead of true previous-day.",
        "Use rise/fall signals as relative momentum indicators, not as causal proof."
      ]
    }
  },
  "summary": {
    "top_polymarket_questions": [
      {
        "question": "Will Bitcoin hit $150k by June 30, 2026?",
        "volume_24h": 5821652.894196,
        "yes_price": 0.0135,
        "market_type": "binary"
      },
      {
        "question": "US x Iran permanent peace deal by April 22, 2026?",
        "volume_24h": 5520100.854613998,
        "yes_price": 0.019,
        "market_type": "binary"
      },
      {
        "question": "Iran x Israel/US conflict ends by April 7?",
        "volume_24h": 4328200.489911007,
        "yes_price": 0.9975,
        "market_type": "binary"
      }
    ],
    "top_google_trends_keywords": [],
    "top_wikipedia_pages": [
      {
        "page": "Kevin_Warsh",
        "views": 98968
      },
      {
        "page": "Donald_Trump",
        "views": 59125
      },
      {
        "page": "Strait_of_Hormuz",
        "views": 22824
      },
      {
        "page": "NATO",
        "views": 6708
      },
      {
        "page": "Russo-Ukrainian_War",
        "views": 2964
      }
    ],
    "recurring_entities_across_sources": [
      "AI",
      "Iran",
      "NATO",
      "Trump"
    ],
    "signal_strength_by_source": {
      "polymarket": "strong",
      "google_trends": "weak",
      "wikipedia_pageviews": "strong"
    },
    "narrative_hints": [
      "Trump-related political / tariff attention is present.",
      "Geopolitical / security attention is present.",
      "AI / regulation / chip attention is present.",
      "Iran-related geopolitical attention is present."
    ],
    "momentum_hints": [
      "Wikipedia risers: Strait_of_Hormuz (+0), Russo-Ukrainian_War (+0), Federal_Reserve (+0)",
      "Polymarket volume risers: Iran x Israel/US conflict ends by April 7? (+117466.4983), Will Roberto Sánchez Palomino win the 2026 Peruvian presidential election? (+71623.8079), Trump out as President by April 30? (+62770.0291)"
    ],
    "prompt_ready_notes": [
      "Use recurring_entities_across_sources to identify themes confirmed by multiple datasets.",
      "Treat Google Trends anchor-normalized values as rough cross-chunk calibration, not exact absolute ranking.",
      "Prefer entities that appear across at least 2 sources when writing the final sentiment brief.",
      "Use delta_vs_previous_day to identify rising vs cooling attention.",
      "If source health is partial or weak, explicitly say evidence is limited."
    ]
  }
}